predictrampydata/__init__.py
predictrampydata/client.py
predictrampydata-0.1.1.dist-info/METADATA
predictrampydata-0.1.1.dist-info/WHEEL
predictrampydata-0.1.1.dist-info/top_level.txt
predictrampydata-0.1.1.dist-info/RECORD
